LICENSE
README.md
setup.py
neirogenius/__init__.py
neirogenius/api.py
neirogenius/attachments.py
neirogenius/errors.py
neirogenius/messages.py
neirogenius/ping.py
neirogenius/settings.py
neirogenius/statistic.py
neirogenius.egg-info/PKG-INFO
neirogenius.egg-info/SOURCES.txt
neirogenius.egg-info/dependency_links.txt
neirogenius.egg-info/requires.txt
neirogenius.egg-info/top_level.txt