Metadata-Version: 2.1
Name: neirogenius
Version: 1.1.0
Summary: Simple wrapper for the Neirogenius API
Home-page: https://github.com/itsSourCream/NeirogeniusPY
Author: itsSourCream
Author-email: me@itssourcream.space
License: Apache License 2.0
Platform: UNKNOWN
License-File: LICENSE
